{
  "updated_at": "2026-07-12T23:02:17Z",
  "mode": "paper",
  "account": {
    "balance_usd": 1008.3683459859094,
    "total_value_usd": 1008.3683459859094,
    "pnl_usd": 2179.74,
    "pnl_pct": -186.08
  },
  "open_positions": [
    {
      "asset": "SOL",
      "size": 0.6494982625921476,
      "entry": 77.05901025,
      "tp": null,
      "sl": null,
      "unrealized_pnl": -0.23804777059721666
    },
    {
      "asset": "NEAR",
      "size": 26.744403733518762,
      "entry": 1.870784925,
      "tp": null,
      "sl": null,
      "unrealized_pnl": 0.674362145970955
    },
    {
      "asset": "ONDO",
      "size": 157.75358889414733,
      "entry": 0.31722353249999996,
      "tp": null,
      "sl": null,
      "unrealized_pnl": 0.831592916863861
    }
  ],
  "last_decision": {
    "at": "2026-07-12T23:02:17Z",
    "asset": "BTC",
    "action": "hold",
    "rationale": "hold-all: empty response"
  }
}
