{
  "updated_at": "2026-07-24T21:40:49Z",
  "mode": "paper",
  "account": {
    "balance_usd": 1063.8293237818598,
    "total_value_usd": 1063.8293237818598,
    "pnl_usd": 5.19,
    "pnl_pct": 0.49
  },
  "open_positions": [
    {
      "asset": "SPY",
      "size": 0.13631035140808592,
      "entry": 733.98681,
      "tp": null,
      "sl": null,
      "unrealized_pnl": 0.0
    },
    {
      "asset": "NVDA",
      "size": 0.48242757556021904,
      "entry": 207.5287125,
      "tp": null,
      "sl": null,
      "unrealized_pnl": 0.0
    },
    {
      "asset": "GOOG",
      "size": -0.3139027529271432,
      "entry": 318.41071500000004,
      "tp": null,
      "sl": null,
      "unrealized_pnl": 0.0
    },
    {
      "asset": "MSFT",
      "size": 0.2600306836206672,
      "entry": 384.8073075,
      "tp": null,
      "sl": null,
      "unrealized_pnl": 0.0
    }
  ],
  "last_decision": {
    "at": "2026-07-24T21:40:49Z",
    "asset": "SPY",
    "action": "hold",
    "rationale": "hold-all: empty response"
  }
}
