{
  "updated_at": "2026-06-12T23:09:28Z",
  "mode": "paper",
  "account": {
    "balance_usd": 1081.065345937121,
    "total_value_usd": 1081.065345937121,
    "pnl_usd": 81.07,
    "pnl_pct": 8.11
  },
  "open_positions": [
    {
      "asset": "VVV",
      "size": -1.9188333493236114,
      "entry": 15.644174,
      "tp": null,
      "sl": null,
      "unrealized_pnl": 2.6991729828264397
    },
    {
      "asset": "VVV",
      "size": 1.9188333493236114,
      "entry": 19.14306675,
      "tp": null,
      "sl": null,
      "unrealized_pnl": -9.41296507723304
    },
    {
      "asset": "VVV",
      "size": 1.9188333493236114,
      "entry": 19.1725815,
      "tp": null,
      "sl": null,
      "unrealized_pnl": -9.46959896382999
    },
    {
      "asset": "VVV",
      "size": 1.9188333493236114,
      "entry": 18.80389725,
      "tp": null,
      "sl": null,
      "unrealized_pnl": -8.762155329559624
    },
    {
      "asset": "VVV",
      "size": 1.9188333493236114,
      "entry": 19.150570499999997,
      "tp": null,
      "sl": null,
      "unrealized_pnl": -9.427363522978023
    },
    {
      "asset": "VVV",
      "size": 1.9188333493236114,
      "entry": 19.347168749999998,
      "tp": null,
      "sl": null,
      "unrealized_pnl": -9.804602801496685
    },
    {
      "asset": "VVV",
      "size": 1.9188333493236114,
      "entry": 19.3246575,
      "tp": null,
      "sl": null,
      "unrealized_pnl": -9.76140746426173
    },
    {
      "asset": "VVV",
      "size": 1.9188333493236114,
      "entry": 20.8874385,
      "tp": null,
      "sl": null,
      "unrealized_pnl": -12.760123764751027
    },
    {
      "asset": "VVV",
      "size": 1.9188333493236114,
      "entry": 20.18258625,
      "tp": null,
      "sl": null,
      "unrealized_pnl": -11.418183344526529
    },
    {
      "asset": "VVV",
      "size": 1.9188333493236114,
      "entry": 20.518254,
      "tp": null,
      "sl": null,
      "unrealized_pnl": -12.062273817518948
    },
    {
      "asset": "VVV",
      "size": 1.9188333493236114,
      "entry": 20.341665749999997,
      "tp": null,
      "sl": null,
      "unrealized_pnl": -11.72343039432025
    },
    {
      "asset": "VVV",
      "size": 1.9188333493236114,
      "entry": 19.23111075,
      "tp": null,
      "sl": null,
      "unrealized_pnl": -9.592460424062171
    },
    {
      "asset": "VVV",
      "size": -1.9188333493236114,
      "entry": 16.412289750000003,
      "tp": null,
      "sl": null,
      "unrealized_pnl": 4.180734433464461
    },
    {
      "asset": "VVV",
      "size": -1.9188333493236114,
      "entry": 16.059966000000003,
      "tp": null,
      "sl": null,
      "unrealized_pnl": 3.504683872205706
    },
    {
      "asset": "VVV",
      "size": -1.9188333493236114,
      "entry": 16.059966000000003,
      "tp": null,
      "sl": null,
      "unrealized_pnl": 3.504683872205706
    },
    {
      "asset": "VVV",
      "size": -1.9188333493236114,
      "entry": 16.059966000000003,
      "tp": null,
      "sl": null,
      "unrealized_pnl": 3.504683872205706
    },
    {
      "asset": "VVV",
      "size": -1.9188333493236114,
      "entry": 16.059966000000003,
      "tp": null,
      "sl": null,
      "unrealized_pnl": 3.504683872205706
    },
    {
      "asset": "VVV",
      "size": -1.9188333493236114,
      "entry": 15.632180000000002,
      "tp": null,
      "sl": null,
      "unrealized_pnl": 2.684793245706613
    },
    {
      "asset": "VVV",
      "size": -1.9188333493236114,
      "entry": 15.62968125,
      "tp": null,
      "sl": null,
      "unrealized_pnl": 2.679998560874989
    },
    {
      "asset": "VVV",
      "size": -1.9188333493236114,
      "entry": 15.62968125,
      "tp": null,
      "sl": null,
      "unrealized_pnl": 2.679998560874989
    }
  ],
  "last_decision": {
    "at": "2026-06-12T23:09:28Z",
    "asset": "BTC",
    "action": "hold",
    "rationale": "hold-all: empty response"
  }
}
