{
  "updated_at": "2026-05-28T21:09:17Z",
  "mode": "paper",
  "account": {
    "balance_usd": 1016.9898875046446,
    "total_value_usd": 1016.9898875046446,
    "pnl_usd": 23.53,
    "pnl_pct": 2.37
  },
  "open_positions": [
    {
      "asset": "AAPL",
      "size": 0.3220560055393633,
      "entry": 310.73528999999996,
      "tp": null,
      "sl": null,
      "unrealized_pnl": 0.5135859325936847
    },
    {
      "asset": "AMZN",
      "size": 0.37242560798480506,
      "entry": 268.78432499999997,
      "tp": null,
      "sl": null,
      "unrealized_pnl": 1.935002420766471
    },
    {
      "asset": "TSLA",
      "size": 0.2325473233803079,
      "entry": 430.23500999999993,
      "tp": null,
      "sl": null,
      "unrealized_pnl": 2.6894074694200456
    },
    {
      "asset": "NVDA",
      "size": -0.2353827323227568,
      "entry": 212.31379,
      "tp": null,
      "sl": null,
      "unrealized_pnl": -0.4298582995951358
    },
    {
      "asset": "GOOG",
      "size": -0.12948000828672052,
      "entry": 385.9669200000001,
      "tp": null,
      "sl": null,
      "unrealized_pnl": -0.044422001242998936
    }
  ],
  "last_decision": {
    "at": "2026-05-28T21:09:17Z",
    "asset": "SPY",
    "action": "buy",
    "rationale": "intraday ema20 indicates a potential buy signal"
  }
}
